{"pXr15RuubClrhw3hgQrecg==":"beichangtan-profile-952x714.jpg","E8s55DTzXX34FxEIMMi1Jg==":"beichangtan-profile-1-952x714.jpg","b9NB5LUpnbM0nl43GUHNqQ==":"beichangtan-profile-1466x1100.jpg","05I0wVMZUCYE9YWBTrPelQ==":"mmexport1534173236075-2000x1348.jpg","ZE1SfOOlFC17P5w5SRbhew==":"mmexport1534173273659-2000x1500.jpg","pR1Pja6gB52NNtyekDsf/g==":"1prof-2000x1346.jpg","nvfcsgoYOR//JaYGGgs79Q==":"mmexport1534173273659-1-2000x1500.jpg","uSF0coHeN5WxVv8UXdiU4A==":"mmexport1534173236075-924x623.jpg","JXEVkaMfEywG9QL4N7ofKw==":"mmexport1534173273659-478x359.jpg","+b1fc+bgQexXSUwlX8qurw==":"mmexport1534173273659-1-478x359.jpg","sOgFPEeCcVff2rrxCC836A==":"mmexport1534173273659-2-478x359.jpg","eN3/WOKNfA9lNGizpNq6mA==":"mmexport1534173236075-1-924x623.jpg","FcUzbY9hznB8LgLZsuJkUw==":"profile-circ-1014x970.png","32Kx8Bzzr6Utw9d4/MxaRg==":"back_beichangtan3-2000x1125.jpg","Bby4+jUy/0MTzvLocq1Dwg==":"tel_aviv_big-1920x1080.jpg","N4czZ4EsiuEY6l3c0uN9Tw==":"tel_aviv_big-1-1920x1080.jpg","YLzRD4pkoXlPLh1LKpGf0Q==":"tel_aviv_big-2-1920x1080.jpg","o7Wn9iSe+CH+Tp8C96h0gQ==":"tel_aviv_big-3-1920x1080.jpg","Mw0bdIEgwiTudGukzmGDJQ==":"tel_aviv_big-4-1920x1080.jpg","TLUAWdTdfsu4GscPggBf1g==":"jumbotron2.jpg","LH3P5ApPWd2IdgCWTtSZWQ==":"prof_headline-1920x473.jpg","zfx1+ITAnsTXr7qYs8zmrw==":"prof_headline-1-1920x473.jpg","vb/I2OZ7IIUBoowIA/Kb7Q==":"prof_headline-2-1920x473.jpg","6tNA+iimZ/HrFezjADY9Vw==":"prof_headline-3-1920x473.jpg","gVMT9gaBxWlVb/escJHZww==":"prof_headline-1920x325.png","WswAbWzFiWZWCmYsBgYt5Q==":"profile-circ-1552x1485.png","aiOXjeIKnETW1FcJLzTzNA==":"profile-circ-small-444x425.png","KJkEqRZL2wDV7cakSC4Ucw==":"profile-circ-small-340x326.png","Aj7/eBXeHEyhAQfZpntwSQ==":"pasted-image-153-532x355.jpg","kfdu8RUrtAATR46js9TCYw==":"pasted-image-158-279x222.jpg","bDArRDcOqo8ZdAnYkHxgPg==":"finalreconstructed-376-90x90.jpg","5vMmKC0192uMTQ7Xogr23g==":"pasted-image-169-478x800.jpg","y2dVPtHUWhaoF6Y4nlUlOw==":"maxwell%20tsai%20-%20rank%20of%20excellence-400-1466x1176.jpg","ZVD4u12HlIKbC16CKEUgLw==":"page4-415-478x682.jpg","PxgQmcGqDHxerXrvKsSrfw==":"screen%20shot%202018-03-09%20at%2011.01.55%20am-282-924x461.png"}